setup.py
cellworld_pid_controller_service/__init__.py
cellworld_pid_controller_service/controller_client.py
cellworld_pid_controller_service.egg-info/PKG-INFO
cellworld_pid_controller_service.egg-info/SOURCES.txt
cellworld_pid_controller_service.egg-info/dependency_links.txt
cellworld_pid_controller_service.egg-info/not-zip-safe
cellworld_pid_controller_service.egg-info/requires.txt
cellworld_pid_controller_service.egg-info/top_level.txt