Metadata-Version: 2.1
Name: cellworld-pid-controller-service
Version: 0.0.11
Summary: PID Controller client
Home-page: UNKNOWN
Author: German Espinosa
Author-email: germanespinosa@gmail.com
License: MIT
Platform: UNKNOWN
